eclipsetools/__init__.py
eclipsetools/filetools.py
eclipsetools/imagetools.py
eclipsetools/tasktools.py
eclipsetools/videotools.py
eclipsetools-0.0.3.dist-info/LICENSE
eclipsetools-0.0.3.dist-info/METADATA
eclipsetools-0.0.3.dist-info/WHEEL
eclipsetools-0.0.3.dist-info/top_level.txt
eclipsetools-0.0.3.dist-info/RECORD
